jinja2_csrf.py
jinja2_csrf-1.0.dist-info/LICENSE
jinja2_csrf-1.0.dist-info/WHEEL
jinja2_csrf-1.0.dist-info/METADATA
jinja2_csrf-1.0.dist-info/RECORD
