Metadata-Version: 2.1
Name: jinja2_csrf
Version: 1.0
Summary: Jinja2 extension to render csrf hidden input
Author-email: Stephan Fitzpatrick <knowsuchagency@gmail.com>
Classifier: License :: OSI Approved :: MIT License
Requires-Dist: jinja2
Project-URL: Home, https://github.com/knowsuchagency/jinja2_csrf
